elevenlabs_mcp/__init__.py
elevenlabs_mcp/database.py
elevenlabs_mcp/elevenlabs_api.py
elevenlabs_mcp/models.py
elevenlabs_mcp/server.py
elevenlabs_mcp_server-0.1.1.dist-info/METADATA
elevenlabs_mcp_server-0.1.1.dist-info/WHEEL
elevenlabs_mcp_server-0.1.1.dist-info/entry_points.txt
elevenlabs_mcp_server-0.1.1.dist-info/licenses/LICENSE
elevenlabs_mcp_server-0.1.1.dist-info/RECORD
