Metadata-Version: 2.4
Name: elevenlabs-mcp-server
Version: 0.1.1
Summary: A Model Context Protocol server providing ElevenLabs text-to-speech integration
Author-email: Mamerto Fabian <aidrivencoder@gmail.com>
License: MIT License
License-File: LICENSE
Keywords: elevenlabs,llm,mcp,text-to-speech,tts
Classifier: Programming Language :: Python :: 3
Classifier: Programming Language :: Python :: 3.11
Requires-Python: >=3.11
Requires-Dist: aiosqlite>=0.19.0
Requires-Dist: mcp>=1.0.0
Requires-Dist: pydub
Requires-Dist: pytest>=8.3.4
Requires-Dist: python-dotenv
Requires-Dist: requests
Requires-Dist: tenacity>=9.0.0
Provides-Extra: dev
Requires-Dist: pytest; extra == 'dev'
Requires-Dist: pytest-asyncio; extra == 'dev'
